{
  "code": "23514",
  "details": "Failing row contains (8dd55027-caa3-4525-88ab-73a3b75f4d3f, 31328c99-9b4a-468d-b3f5-908ffeba9abb, Test Project - E2E Workflow, End-to-end test project, {Testing,QA}, 400.00, active, dd806503-6cec-48a1-9c90-26c97d840831, 2025-11-29 11:03:40.397009, 2025-11-29 11:03:40.397009, [{\"name\": \"Milestone 1\", \"amount\": 200, \"description\": \"First de..., 0.00).",
  "hint": null,
  "message": "new row for relation \"projects\" violates check constraint \"projects_status_check\""
}